{
  "kaynak": "bilet.ucuzaucak.net",
  "veri": [
    {
      "bilet": "İzmir Adana Uçak Bileti",
      "yon": "Gidiş Dönüş",
      "fiyat": "640 TL",
      "tarih": "Aralık, Kasım",
      "paylasim": "4 dakika önce paylaşıldı",
      "link": "https://bilet.ucuzaucak.net/f/izmir-adana-ucak-bileti--15ftv2"
    },
    {
      "bilet": "İstanbul Priştine Uçak Bileti",
      "yon": "Gidiş Dönüş",
      "fiyat": "1120 TL",
      "tarih": "Aralık, Kasım, Temmuz, Haziran, Mayıs, Nisan, Mart, Şubat, Ocak",
      "paylasim": "22 saat önce.",
      "link": "https://bilet.ucuzaucak.net/f/istanbul-pristine-ucak-bileti--15ftv1"
    },
    {
      "bilet": "İstanbul New York Uçak Bileti",
      "yon": "Gidiş Dönüş",
      "fiyat": "6726 TL",
      "tarih": "Aralık, Kasım, Ekim, Mart, Şubat, Ocak",
      "paylasim": "Dün paylaşıldı",
      "link": "https://bilet.ucuzaucak.net/f/istanbul-new-york-ucak-bileti--15ftv0"
    },
    {
      "bilet": "İstanbul Düsseldorf/Eindhoven Uçak Bileti",
      "yon": "Gidiş Dönüş",
      "fiyat": "858 TL",
      "tarih": "Aralık, Kasım, Mart, Şubat, Ocak",
      "paylasim": "Dün paylaşıldı",
      "link": "https://bilet.ucuzaucak.net/f/istanbul-dusseldorf-eindhoven-ucak-bileti--15ftuz"
    },
    {
      "bilet": "İstanbul Tiflis Uçak Bileti",
      "yon": "Gidiş Dönüş",
      "fiyat": "924 TL",
      "tarih": "Aralık, Mart, Şubat, Ocak",
      "paylasim": "Bu hafta paylaşıldı",
      "link": "https://bilet.ucuzaucak.net/f/istanbul-tiflis-ucak-bileti--15ftuy"
    },
    {
      "bilet": "İstanbul Priştine/Tiran Uçak Bileti",
      "yon": "Gidiş Dönüş",
      "fiyat": "667 TL",
      "tarih": "Aralık, Mart, Şubat, Ocak",
      "paylasim": "Bu hafta paylaşıldı",
      "link": "https://bilet.ucuzaucak.net/f/istanbul-pristine-tiran-ucak-bileti--15ftux"
    },
    {
      "bilet": "İstanbul Atina/Seyşeller Uçak Bileti",
      "yon": "Gidiş Dönüş",
      "fiyat": "5600 TL",
      "tarih": "Aralık, Mart, Şubat, Ocak",
      "paylasim": "Bu hafta paylaşıldı",
      "link": "https://bilet.ucuzaucak.net/f/istanbul-atina-seyseller-ucak-bileti--15ftuw"
    },
    {
      "bilet": "İstanbul Atina Uçak Bileti",
      "yon": "Gidiş Dönüş",
      "fiyat": "1012 TL",
      "tarih": "Aralık, Mart, Şubat, Ocak",
      "paylasim": "Bu hafta paylaşıldı",
      "link": "https://bilet.ucuzaucak.net/f/istanbul-atina-ucak-bileti--15ftuv"
    },
    {
      "bilet": "İstanbul Venedik Uçak Bileti",
      "yon": "Gidiş Dönüş",
      "fiyat": "850 TL",
      "tarih": "Aralık, Mart, Şubat, Ocak",
      "paylasim": "Bu hafta paylaşıldı",
      "link": "https://bilet.ucuzaucak.net/f/istanbul-venedik-ucak-bileti--15ftuu"
    },
    {
      "bilet": "İzmir Londra Uçak Bileti",
      "yon": "Gidiş Dönüş",
      "fiyat": "974 TL",
      "tarih": "Aralık, Mart, Şubat, Ocak",
      "paylasim": "Bu hafta paylaşıldı",
      "link": "https://bilet.ucuzaucak.net/f/izmir-londra-ucak-bileti--15ftut"
    },
    {
      "bilet": "İstanbul Viyana Uçak Bileti",
      "yon": "Gidiş Dönüş",
      "fiyat": "1154 TL",
      "tarih": "Aralık, Kasım, Mart, Şubat, Ocak",
      "paylasim": "Bu hafta paylaşıldı",
      "link": "https://bilet.ucuzaucak.net/f/istanbul-viyana-ucak-bileti--15ftus"
    },
    {
      "bilet": "İstanbul Bologna Uçak Bileti",
      "yon": "Gidiş Dönüş",
      "fiyat": "734 TL",
      "tarih": "Aralık, Kasım, Şubat, Ocak",
      "paylasim": "Bu hafta paylaşıldı",
      "link": "https://bilet.ucuzaucak.net/f/istanbul-bologna-ucak-bileti--15ftur"
    },
    {
      "bilet": "İstanbul Üsküp Uçak Bileti",
      "yon": "Gidiş Dönüş",
      "fiyat": "710 TL",
      "tarih": "Aralık, Kasım, Mart, Şubat, Ocak",
      "paylasim": "Bu hafta paylaşıldı",
      "link": "https://bilet.ucuzaucak.net/f/istanbul-uskup-ucak-bileti--15ftuq"
    },
    {
      "bilet": "İstanbul Saraybosna Uçak Bileti",
      "yon": "Gidiş Dönüş",
      "fiyat": "762 TL",
      "tarih": "Aralık, Mart, Şubat, Ocak",
      "paylasim": "Bu hafta paylaşıldı",
      "link": "https://bilet.ucuzaucak.net/f/istanbul-saraybosna-ucak-bileti--15ftup"
    },
    {
      "bilet": "Ankara Tahran Uçak Bileti",
      "yon": "Gidiş Dönüş",
      "fiyat": "516 TL",
      "tarih": "Aralık, Kasım, Mart, Şubat, Ocak",
      "paylasim": "Bu hafta paylaşıldı",
      "link": "https://bilet.ucuzaucak.net/f/ankara-tahran-ucak-bileti--15ftuo"
    },
    {
      "bilet": "İstanbul Köln Uçak Bileti",
      "yon": "Gidiş Dönüş",
      "fiyat": "1072 TL",
      "tarih": "Aralık, Kasım, Şubat, Ocak",
      "paylasim": "Bu hafta paylaşıldı",
      "link": "https://bilet.ucuzaucak.net/f/istanbul-koln-ucak-bileti--15ftun"
    },
    {
      "bilet": "İstanbul Budapeşte Uçak Bileti",
      "yon": "Gidiş Dönüş",
      "fiyat": "1027 TL",
      "tarih": "Aralık, Kasım, Mart, Şubat, Ocak",
      "paylasim": "Bu hafta paylaşıldı",
      "link": "https://bilet.ucuzaucak.net/f/istanbul-budapeste-ucak-bileti--15ftum"
    },
    {
      "bilet": "İstanbul Brüksel Uçak Bileti",
      "yon": "Gidiş Dönüş",
      "fiyat": "466 TL",
      "tarih": "Aralık, Kasım, Mart, Şubat, Ocak",
      "paylasim": "Bu hafta paylaşıldı",
      "link": "https://bilet.ucuzaucak.net/f/istanbul-bruksel-ucak-bileti--15ftul"
    },
    {
      "bilet": "İstanbul Barcelona Uçak Bileti",
      "yon": "Gidiş Dönüş",
      "fiyat": "778 TL",
      "tarih": "Aralık, Mart, Şubat, Ocak",
      "paylasim": "Bu hafta paylaşıldı",
      "link": "https://bilet.ucuzaucak.net/f/istanbul-barcelona-ucak-bileti--15ftuk"
    },
    {
      "bilet": "İstanbul Prag Uçak Bileti",
      "yon": "Gidiş Dönüş",
      "fiyat": "902 TL",
      "tarih": "Aralık, Kasım, Mart, Şubat, Ocak",
      "paylasim": "Bu hafta paylaşıldı",
      "link": "https://bilet.ucuzaucak.net/f/istanbul-prag-ucak-bileti--15ftuj"
    },
    {
      "bilet": "İstanbul Basel Uçak Bileti",
      "yon": "Gidiş Dönüş",
      "fiyat": "824 TL",
      "tarih": "Aralık, Kasım, Mart, Şubat, Ocak",
      "paylasim": "Bu hafta paylaşıldı",
      "link": "https://bilet.ucuzaucak.net/f/istanbul-basel-ucak-bileti--15ftui"
    },
    {
      "bilet": "Konya Kopenhag Uçak Bileti",
      "yon": "Gidiş Dönüş",
      "fiyat": "562 TL",
      "tarih": "Aralık, Kasım, Mart, Şubat, Ocak",
      "paylasim": "Bu hafta paylaşıldı",
      "link": "https://bilet.ucuzaucak.net/f/konya-kopenhag-ucak-bileti--15ftuh"
    },
    {
      "bilet": "İstanbul Belgrad/Kraljevo/Niş Uçak Bileti",
      "yon": "Gidiş Dönüş",
      "fiyat": "1660 TL",
      "tarih": "Ekim, Eylül",
      "paylasim": "Paylaşalı çok oldu",
      "link": "https://bilet.ucuzaucak.net/f/istanbul-belgrad-kraljevo-nis-ucak-bileti--15ftug"
    },
    {
      "bilet": "İstanbul Kolombo Uçak Bileti",
      "yon": "Gidiş Dönüş",
      "fiyat": "8400 TL",
      "tarih": "Ekim",
      "paylasim": "Paylaşalı çok oldu",
      "link": "https://bilet.ucuzaucak.net/f/istanbul-kolombo-ucak-bileti--15ftuf"
    },
    {
      "bilet": "İstanbul Kopenhag Uçak Bileti",
      "yon": "Gidiş Dönüş",
      "fiyat": "1655 TL",
      "tarih": "Aralık, Kasım, Ekim, Nisan, Mart",
      "paylasim": "Paylaşalı çok oldu",
      "link": "https://bilet.ucuzaucak.net/f/istanbul-kopenhag-ucak-bileti--15ftue"
    }
  ]
}